{
    "name": "阿里巴巴",
    "children": [{
        "name": "公司及子公司",
        "children": [{
            "name": "Alibaba Group Holding Limited（阿里巴巴集团控股公司）",
            "description": "注册地：开曼群岛；注册时间：1999年6月28日"
        }, {
            "name": "Taobao Holding Limited（淘宝控股公司）",
            "description": "注册地：开曼群岛；备注：阿里集团全资子公司，中华人民共和国境内淘宝市场和天猫平台相关子公司的非直接控股公司"
        }, {
            "name": "Taobao China Holding Limited（淘宝中国控股公司）",
            "description": "注册地：香港；性质：有限责任公司；备注：Taobao Holding Limited的全资子公司，中华人民共和国境内淘宝市场和天猫平台以及天猫国际等海外业务的直接控股公司"
        }, {
            "name": "Taobao (China) Software Co.,Ltd.（淘宝（中国）软件有限公司）",
            "description": "注册地：中国；性质：有限责任公司（台港澳独资）；统一社会信用代码：913301007682254698；登记日期：2004年12月7日；法定代表人：张勇；注册资本：37,500(万美元)；所属地区：杭州市；地址：杭州市余杭区五常街道荆丰村；所属行业：数据处理和存储服务、信息系统集成服务；经营范围；研究、开发计算机软、硬件，网络技术产品，多媒体产品；系统集成的设计、调试及维护；销售自身开发的产品；并提供计算机技术咨询、服务，电子商务平台支持；经济信息咨询（含商品中介）（国家禁止和限制的除外，凡涉及许可证制度的凭证经营）；股东信息：淘宝中国控股有限公司独资",
            "children": [{
                "name": "分公司",
                "children": [{
                    "name": "淘宝（中国）软件有限公司北京朝阳分公司",
                    "description": "性质：分公司；法定代表人：吴泳铭；登记日期：2009年3月10日；所属地区：北京市；地址：北京市朝阳区西大望路甲12号（国家广告产业园区）A座7层；所属行业：其他专业咨询、企业总部管理"
                }, {
                    "name": "淘宝（中国）软件有限公司杭州分公司",
                    "description": "性质：有限责任公司分支机构；统一社会信用代码：913301000536684269；法定代表人：张春晖；登记日期：2012年9月6日；所属地区：杭州市；地址：杭州市西湖区西溪新座5幢901室；所属行业：其他专业咨询、企业总部管理"
                }]
            }, {
                "name": "高层管理",
                "children": [{
                    "name": "张勇",
                    "description": "董事长兼总经理"
                }, {
                    "name": "蒋芳",
                    "description": "董事"
                }, {
                    "name": "郑俊芳",
                    "description": "监事"
                }, {
                    "name": "武卫",
                    "description": "董事"
                }, {
                    "name": "戴珊"
                }, {
                    "name": "陆兆禧"
                }]
            }, {
                "name": "对外投资",
                "children": [{
                    "name": "阿里未来酒店管理（浙江）有限公司",
                    "description": ""
                }, {
                    "name": "浙江阿里巴巴通信技术有限公司",
                    "description": ""
                }, {
                    "name": "北京淘宝科技有限公司",
                    "description": ""
                }, {
                    "name": "阿里巴巴（海南）数娱有限公司",
                    "description": ""
                }, {
                    "name": "南京淘宝软件有限公司",
                    "description": ""
                }]
            }]
        }, {
            "name": "Zhejiang Tmall Technology Co.,Ltd.（浙江天猫技术有限公司）",
            "description": "注册地：中国；性质：有限责任公司（台港澳独资）；统一社会信用代码：91330100563015652A；法定代表人：张勇；登记日期：2010年10月25日；注册资本：4,900（万美元）；所属地区：杭州市；地址：杭州余杭区五常街道五常大道168号二层；所属行业：技术推广服务、互联网信息服务；经营范围：研发（网络商城技术、计算机软硬件、网络技术产品、多媒体产品），服务（系统集成的设计、调试及维护），提供计算机技术咨询、服务电子商务平台支持，经济信息咨询（含商品中介），成年人的非证书劳动职业技能培训和成年人的非文化教育培训（涉及前置审批的项目除外）（涉及国家规定实施准入特别管理措施的除外）；股东：淘宝中国控股有限公司独资；实缴：200万美元",
            "children": [{
                "name": "高层管理",
                "children": [{
                    "name": "张勇",
                    "description": "董事长兼总经理"
                }, {
                    "name": "蒋芳",
                    "description": "董事"
                }, {
                    "name": "郑俊芳",
                    "description": "监事"
                }, {
                    "name": "武卫",
                    "description": "董事"
                }, {
                    "name": "戴珊"
                }, {
                    "name": "陆兆禧"
                }]
            }, {
                "name": "对外投资",
                "children": [{
                    "name": "南京云安信息有限公司"
                }, {
                    "name": "贵州阿里云计算有限公司"
                }, {
                    "name": "南京翰海源信息技术有限公司"
                }, {
                    "name": "郑州阿里云计算有限公司"
                }, {
                    "name": "北京阿里巴巴信息技术有限公司"
                }, {
                    "name": "阿里巴巴（北京）软件服务有限公司"
                }, {
                    "name": "阿里云计算（苏州）有限公司"
                }, {
                    "name": "浙江天猫供应链管理有限公司"
                }]
            }]
        }, {
            "name": "Alibaba.com Limited（阿里巴巴网络有限公司）",
            "description": "注册地：开曼群岛；性质：有限责任公司；备注：中华人民共和国境内与Alibaba.com、1688.com和AliExpress相关业务子公司的非直接控股公司"
        }, {
            "name": "Alibaba.com Investment Holding Limited",
            "description": "注册地：英属维尔京群岛；注册时间：2006年；性质：有限责任公司；备注：Alibaba.com Limited的全资子公司，中华人民共和国境内淘宝市场和天猫平台以及天猫国际等海外业务的较低一级的控股公司"
        }, {
            "name": "Alibaba Investment Limited",
            "description": "注册地：英属维尔京群岛；性质：有限责任公司；备注：阿里集团全资子公司，阿里集团投资战略的主要控股公司"
        }, {
            "name": "Alibaba.com China Limited",
            "description": "注册地：香港；注册时间：2006年10月5日"
        }, {
            "name": "阿里巴巴（中国）网络技术有限公司",
            "description": "注册地：中国；性质：有限责任公司（台港澳独资）；统一社会信用代码：91330100716105852F；法定代表人：张勇；登记日期：1999年9月9日；注册资本：57,690（万美元）；股东：Alibaba.com China Limited（100%）；所属地区：杭州市；地址：杭州市滨江区网商路699号；所属行业：其他未列明教育、科技中介服务；经营范围：开发、销售计算机网络应用软件；设计、制作、加工计算机网络产品并提供相关技术服务和咨询服务等",
            "children": [{
                "name": "分公司",
                "children": [{
                    "name": "阿里巴巴（中国）网络技术有限公司石家庄分公司"
                }, {
                    "name": "阿里巴巴（中国）网络技术有限公司大连分公司"
                }, {
                    "name": "阿里巴巴（中国）网络技术有限公司东莞分公司"
                }, {
                    "name": "阿里巴巴（中国）网络技术有限公司天津分公司"
                }, {
                    "name": "阿里巴巴（中国）网络技术有限公司佛山分公司"
                }, {
                    "name": "阿里巴巴（中国）网络技术有限公司济南分公司"
                }, {
                    "name": "阿里巴巴（中国）网络技术有限公司绍兴分公司"
                }, {
                    "name": "阿里巴巴（中国）网络技术有限公司常州分公司"
                }, {
                    "name": "阿里巴巴（中国）网络技术有限公司北京分公司"
                }, {
                    "name": "阿里巴巴（中国）网络技术有限公司广州分公司"
                }, {
                    "name": "阿里巴巴（中国）网络技术有限公司宁波分公司"
                }, {
                    "name": "阿里巴巴（中国）网络技术有限公司温州分公司"
                }, {
                    "name": "阿里巴巴（中国）网络技术有限公司深圳分公司"
                }, {
                    "name": "阿里巴巴（中国）网络技术有限公司青岛分公司"
                }, {
                    "name": "阿里巴巴（中国）网络技术有限公司苏州分公司"
                }, {
                    "name": "阿里巴巴（中国）网络技术有限公司台州分公司"
                }, {
                    "name": "阿里巴巴（中国）网络技术有限公司中山分公司"
                }, {
                    "name": "阿里巴巴（中国）网络技术有限公司上海分公司"
                }, {
                    "name": "阿里巴巴（中国）网络技术有限公司义乌分公司"
                }, {
                    "name": "阿里巴巴（中国）网络技术有限公司南通分公司"
                }, {
                    "name": "阿里巴巴（中国）网络技术有限公司福州分公司"
                }, {
                    "name": "阿里巴巴（中国）网络技术有限公司成都分公司"
                }, {
                    "name": "阿里巴巴（中国）网络技术有限公司厦门分公司"
                }]
            }, {
                "name": "高层管理",
                "children": [{
                    "name": "张勇",
                    "description": "董事长兼总经理"
                }, {
                    "name": "蒋芳",
                    "description": "董事"
                }, {
                    "name": "郑俊芳",
                    "description": "监事"
                }, {
                    "name": "武卫",
                    "description": "董事"
                }, {
                    "name": "戴珊"
                }, {
                    "name": "陆兆禧"
                }]
            }, {
                "name": "对外投资",
                "children": [{
                    "name": "苏州思必驰信息科技有限公司"
                }, {
                    "name": "深圳市一达通企业服务有限公司"
                }, {
                    "name": "永杨安风（北京）科技股份有限公司"
                }, {
                    "name": "北京新雅在线信息技术有限公司"
                }, {
                    "name": "上海易果电子商务有限公司"
                }, {
                    "name": "杭州魅投信息技术有限公司"
                }, {
                    "name": "上海驻云信息科技有限公司"
                }, {
                    "name": "北京接我科技有限公司"
                }, {
                    "name": "南京晟邦物流有限公司"
                }, {
                    "name": "厦门又一城软件科技有限公司"
                }, {
                    "name": "深圳市瑞云科技有限公司"
                }, {
                    "name": "广州恒大淘宝足球队俱乐部股份有限公司"
                }, {
                    "name": "上海幻橙网络科技有限公司"
                }, {
                    "name": "径圆（上海）信息技术有限公司"
                }, {
                    "name": "北京雅观科技有限公司"
                }, {
                    "name": "杭州界内电子商务有限公司"
                }, {
                    "name": "杭州数梦工场科技有限公司"
                }, {
                    "name": "上海赛为投资中心（有限合伙）"
                }, {
                    "name": "杭州源牛电子商务有限公司"
                }, {
                    "name": "微鲸科技有限公司"
                }, {
                    "name": "上海智篆文化传播有限公司"
                }, {
                    "name": "北京缔元信互联网数据技术有限公司"
                }, {
                    "name": "浙江心怡科技供应链管理有限公司"
                }, {
                    "name": "上海丽人丽妆换妆品股份有限公司"
                }, {
                    "name": "百越文化创意有限公司"
                }, {
                    "name": "上海多维度网络科技股份有限公司"
                }, {
                    "name": "上海庆科信息技术有限公司"
                }, {
                    "name": "北京百舜年文化传播有限公司"
                }, {
                    "name": "厦门享动网络科技有限公司"
                }, {
                    "name": "浙江伍一技术股份有限公司"
                }, {
                    "name": "杭州溢六发发广告有限公司"
                }]
            }]
        }, {
            "name": "阿里巴巴（中国）教育科技有限公司",
            "description": "注册地：中国；性质：有限责任公司（台港澳独资）；统一社会信用代码：91330108694564694C；法定代表人：吴敏芝；登记日期：2009年9月21日；注册资本：100（万美元）；所属地区：杭州市；地址：杭州市滨江区网商路699号6号楼2楼；所属行业：其他未列明教育、职业技能培训；股东：Alibaba.com China Limited；实缴：100万美元",
            "children": [{
                "name": "高层管理",
                "children": [{
                    "name": "吴敏芝",
                    "description": "董事长兼总经理",
                    "children": [{
                        "name": "阿里巴巴（中国）软件有限公司",
                        "description": "董事长兼总经理，法人"
                    }, {
                        "name": "阿里巴巴（中国）网络技术有限公司佛山分公司",
                        "description": "法人"
                    }, {
                        "name": "浙江一达通企业服务有限公司",
                        "description": "执行董事"
                    }, {
                        "name": "杭州君澳股权投资合伙企业（有限合伙）",
                        "description": "投资人"
                    }, {
                        "name": "山东一达通企业服务有限公司",
                        "description": "执行董事，法人"
                    }, {
                        "name": "福建一达通企业服务有限公司",
                        "description": "执行董事，法人"
                    }]
                }, {
                    "name": "戴珊",
                    "description": "董事"
                }, {
                    "name": "武卫",
                    "description": "董事"
                }, {
                    "name": "郑俊芳",
                    "description": "监事"
                }, {
                    "name": "陆兆禧"
                }]
            }, {
                "name": "对外投资",
                "children": [{
                    "name": "阿里巴巴（成都）教育软件有限公司"
                }]
            }]
        }, {
            "name": "阿里巴巴（中国）软件有限公司",
            "description": "注册地：中国；性质：有限责任公司（台港澳独资）；统一社会信用代码：91330100759521215A；法人：吴敏芝；登记日期：2004年8月23日；注册资本：100（万美元）；所属地区：杭州；地址：杭州市滨江区网商路699号7号楼5楼；所属行业：五金产品批发、家用电器批发；股东：Alibaba.com China Limited；实缴：100万美元"
        }, {
            "name": "杭州阿里妈妈网络技术有限公司",
            "description": "注册地：中国；性质：有限责任公司（台港澳独资）；统一社会信用代码：9133010066802984X7；法人：朱顺炎；登记时间2007年12月6日；注册资本：50（万美元）；所属地区：杭州；地址：杭州市西湖区西斗门路3号天堂软件园A幢9楼G座；所属行业：技术推广服务、软件开发；股东：阿里妈妈中国控股有限公司；实缴：50万美元",
            "children": [{
                "name": "高层管理",
                "children": [{
                    "name": "朱顺炎",
                    "description": "董事长兼总经理",
                    "children": [{
                        "name": "杭州阿里科技有限公司",
                        "description": "董事长兼总经理，法人"
                    }, {
                        "name": "广州市动景计算机科技有限公司",
                        "description": "监事，投资人"
                    }, {
                        "name": "优视科技（中国）有限公司",
                        "description": "监事"
                    }]
                }]
            }, {
                "name": "对外投资",
                "children": [{
                    "name": "杭州阿里妈妈软件服务有限公司"
                }, {
                    "name": "杭州舜易广告有限公司"
                }]
            }]
        }]
    }, {
        "name": "主体业务",
        "children": [{
            "name": "Retail Commerce in China",
            "children": [{
                "name": "Taobao.com（淘宝网）"
            }, {
                "name": "Tmall.com（天猫）"
            }, {
                "name": "Juhuasuan.com（聚划算）"
            }, {
                "name": "Rural Taobao（cun.taobao.com 农村淘宝）"
            }]
        }, {
            "name": "Wholesale Commerce in China",
            "children": [{
                "name": "1688.com（阿里巴巴）"
            }]
        }, {
            "name": "International and Cross-border Commerce",
            "children": [{
                "name": "AliExpress.com（速卖通）"
            }, {
                "name": "Tmall Global（天猫国际）"
            }, {
                "name": "Alibaba.com"
            }, {
                "name": "Lazada"
            }]
        }, {
            "name": "Cloud Computing",
            "children": [{
                "name": "UCWeb"
            }, {
                "name": "YoukuTudou"
            }, {
                "name": "Tmall TV"
            }, {
                "name": "Alibaba Music（阿里音乐）"
            }, {
                "name": "Alisports.com（阿里体育）"
            }]
        }, {
            "name": "Other Innovation Initiatives",
            "children": [{
                "name": "YunOS"
            }, {
                "name": "高德"
            }, {
                "name": "Dingtalk.com（钉钉）"
            }, {
                "name": "AliHealth（阿里健康）"
            }]
        }]
    }]
}